{
	"vulinfoid": "JVNDB-2019-010288",
	"vulinfodata": {
		"title": "複数の Apple 製品における脆弱性に対するアップデート",
		"vulinfodescription": {
			"overview": "Apple から各製品向けのアップデートが公開されました。 "
		},
		"affected": {
			"affecteditem": [
				{
					"name": "アップル",
					"productname": "iCloud",
					"cpe": {
						"text": "cpe:/a:apple:icloud",
						"version": "2.2"
					},
					"versionnumber": [
						"for Windows 10.7 より前のバージョン",
						"for Windows 7.14 より前のバージョン"
					]
				},
				{
					"name": "アップル",
					"productname": "iTunes",
					"cpe": {
						"text": "cpe:/a:apple:itunes",
						"version": "2.2"
					},
					"versionnumber": [
						"12.10.1 for Windows より前のバージョン"
					]
				},
				{
					"name": "アップル",
					"productname": "macOS Catalina",
					"cpe": {
						"text": "cpe:/o:apple:mac_os_catalina",
						"version": "2.2"
					},
					"versionnumber": [
						"10.15 より前のバージョン"
					]
				}
			]
		},
		"impact": {
			"impactitem": {
				"description": "想定される影響は各脆弱性により異なりますが、次のような影響を受ける可能性があります。  * 任意のコード実行 * サービス運用妨害 (DoS) * 情報漏えい * 認証回避 * アクセス制限回避"
			}
		},
		"solution": {
			"solutionitem": {
				"description": "[アップデートする] Apple が提供する情報をもとに最新版へアップデートしてください。 "
			}
		},
		"related": {
			"relateditem": [
				{
					"type": "vendor",
					"name": "Apple Security Updates",
					"vulinfoid": "About the security content of iCloud for Windows 10.7",
					"url": "https://support.apple.com/en-us/HT210636"
				},
				{
					"type": "vendor",
					"name": "Apple Security Updates",
					"vulinfoid": "About the security content of iCloud for Windows 7.14",
					"url": "https://support.apple.com/en-us/HT210637"
				},
				{
					"type": "vendor",
					"name": "Apple Security Updates",
					"vulinfoid": "About the security content of macOS Catalina 10.15",
					"url": "https://support.apple.com/en-us/HT210634"
				},
				{
					"type": "vendor",
					"name": "Apple Security Updates",
					"vulinfoid": "About the security content of iTunes 12.10.1 for Windows",
					"url": "https://support.apple.com/en-us/HT210635"
				},
				{
					"type": "advisory",
					"name": "JVN",
					"vulinfoid": "JVNVU#90484857",
					"url": "https://jvn.jp/vu/JVNVU90484857/"
				}
			]
		},
		"history": {
			"historyitem": [
				{
					"historyno": "1",
					"datetime": "2019-10-10T12:32:16+09:00",
					"description": "[2019年10月10日]\\n  掲載"
				}
			]
		},
		"datefirstpublished": "2019-10-10T12:32:16+09:00",
		"datelastupdated": "2019-10-10T12:32:16+09:00",
		"datepublic": "2019-10-09T00:00:00+09:00"
	}
}
