{
  "vulinfoid": "JVNDB-2010-002077",
  "vulinfodata": {
    "title": "Accela BizSearch の文書参照画面におけるフィッシング脅威の脆弱性",
    "vulinfodescription": {
      "overview": "Accela BizSearch ゲートウェイオプションの文書参照画面には、下記の脆弱性が存在します。 * 本物のページ上に、偽のページが表示される脆弱性が存在します。 * ブラウザが保存している Cookie を第三者に盗まれる脆弱性が存在します。 * 任意の Cookie をブラウザに保存させられる脆弱性が存在します。"
    },
    "affected": {
      "affecteditem": [
        {
          "name": "アクセラテクノロジ",
          "productname": "Accela BizSearch",
          "cpe": {
            "text": "cpe:/a:accelatech:bizsearch",
            "version": "2.2"
          },
          "versionnumber": [
            "V3.0 ゲートウェイオプション NTFS ACL用",
            "V3.0 ゲートウェイオプション TeamWARE用",
            "V3.1 ゲートウェイオプション NTFS ACL用",
            "V3.1 ゲートウェイオプション TeamWARE用"
          ]
        },
        {
          "name": "アクセラテクノロジ",
          "productname": "eAccela BizSearch",
          "cpe": {
            "text": "cpe:/a:accelatech:accelatech_eaccela_bizsearch",
            "version": "2.2"
          },
          "versionnumber": [
            "V1.0 ゲートウェイオプション NTFS ACL用",
            "V1.0 ゲートウェイオプション TeamWARE用",
            "V2.0 ゲートウェイオプション NTFS ACL用",
            "V2.0 ゲートウェイオプション TeamWARE用",
            "V2.1 ゲートウェイオプション NTFS ACL用",
            "V2.1 ゲートウェイオプション TeamWARE用"
          ]
        },
        {
          "name": "富士通",
          "productname": "IntelligentSearch",
          "cpe": {
            "text": "cpe:/a:fujitsu:intelligentsearch",
            "version": "2.2"
          },
          "versionnumber": [
            "ゲートウェイオプション 2.0",
            "ゲートウェイオプション 2.0.1",
            "ゲートウェイオプション for WindowsNT V2.0L10",
            "ゲートウェイオプション for WindowsNT V2.0L20"
          ]
        }
      ]
    },
    "impact": {
      "cvss": [
        {
          "version": "2.0",
          "severity": {
            "text": "Medium",
            "type": "Base"
          },
          "base": "5.8",
          "vector": "AV:N/AC:M/Au:N/C:P/I:P/A:N"
        }
      ],
      "impactitem": {
        "description": "第三者により、本物のページ上に偽のページが表示される、ブラウザが保存している Cookie を盗まれる、または、任意の Cookie をブラウザに保存させられる脆弱性が存在します。"
      }
    },
    "solution": {
      "solutionitem": {
        "description": "ベンダ情報及び参考情報を参照して適切な対策を実施してください。"
      }
    },
    "related": {
      "relateditem": [
        {
          "type": "vendor",
          "name": "Accela Technology Corporation",
          "vulinfoid": "Top Page",
          "url": "http://www.accelatech.com/"
        },
        {
          "type": "vendor",
          "name": "富士通 セキュリティ情報",
          "vulinfoid": "bizsearch201002",
          "url": "http://software.fujitsu.com/jp/security/products-fujitsu/solution/bizsearch201002.html"
        },
        {
          "type": "cwe",
          "name": "JVNDB",
          "vulinfoid": "CWE-noinfo",
          "url": "https://www.ipa.go.jp/security/vuln/scap/cwe.html",
          "title": "情報不足"
        }
      ]
    },
    "history": {
      "historyitem": [
        {
          "historyno": "0",
          "datetime": "2018-02-17T10:37:52+09:00",
          "description": "[2010年10月01日]\\n  掲載"
        }
      ]
    },
    "datefirstpublished": "2010-10-01T17:37:25+09:00",
    "datelastupdated": "2010-10-01T17:37:25+09:00",
    "datepublic": "2010-09-02T00:00:00+09:00"
  }
}
