{
	"vulinfoid": "JVNDB-2011-000037",
	"vulinfodata": {
		"title": "Internet Explorer におけるクリップボードの操作に関する脆弱性",
		"vulinfodescription": {
			"overview": "Internet Explorer には、クリップボードの操作に関する脆弱性が存在します。  Internet Explorer には、クリップボードの操作に関する脆弱性が存在します。このため、Internet Explorer を特定の設定で使用すると、ウェブサイト側からクリップボードの内容を読み書きされてしまう可能性があります。  この脆弱性情報は、情報セキュリティ早期警戒パートナーシップに基づき下記の方が IPA に報告し、JPCERT/CC が開発者との調整を行いました。 報告者: スターダスト 星屑 氏"
		},
		"affected": {
			"affecteditem": [
				{
					"name": "マイクロソフト",
					"productname": "Microsoft Internet Explorer",
					"cpe": {
						"text": "cpe:/a:microsoft:internet_explorer",
						"version": "2.2"
					},
					"versionnumber": [
						"6 およびそれ以前のバージョン"
					]
				}
			]
		},
		"impact": {
			"cvss": [
				{
					"version": "2.0",
					"severity": {
						"text": "Medium",
						"type": "Base"
					},
					"base": "5.8",
					"vector": "AV:N/AC:M/Au:N/C:P/I:P/A:N"
				}
			],
			"impactitem": {
				"description": "クリップボードの内容が漏えいしたり、改ざんされたりする可能性があります。"
			}
		},
		"solution": {
			"solutionitem": {
				"description": "[アップデートする] 開発者が提供する情報をもとに最新版へアップデートを行ってください。"
			}
		},
		"related": {
			"relateditem": [
				{
					"type": "vendor",
					"name": "Microsoft サポート",
					"vulinfoid": "JP224993",
					"url": "http://support.microsoft.com/kb/224993"
				},
				{
					"type": "advisory",
					"name": "JVN",
					"vulinfoid": "JVN#63451350",
					"url": "http://jvn.jp/jp/JVN63451350/index.html"
				},
				{
					"type": "cwe",
					"name": "JVNDB",
					"vulinfoid": "CWE-Other",
					"url": "https://www.ipa.go.jp/security/vuln/scap/cwe.html",
					"title": "その他"
				}
			]
		},
		"history": {
			"historyitem": [
				{
					"historyno": "0",
					"datetime": "2018-02-17T10:37:52+09:00",
					"description": "[2011年06月15日]\\n  掲載"
				}
			]
		},
		"datefirstpublished": "2011-06-15T14:15:12+09:00",
		"datelastupdated": "2011-06-15T14:15:12+09:00",
		"datepublic": "2011-06-15T00:00:00+09:00"
	}
}
