{
	"vulinfoid": "JVNDB-2021-001345",
	"vulinfodata": {
		"title": "Cosminexus 運用管理機能における情報露出の脆弱性",
		"vulinfodescription": {
			"overview": "Cosminexus 運用管理機能に、Management Server に関する情報が露出する脆弱性が存在します。  "
		},
		"affected": {
			"affecteditem": [
				{
					"name": "日立",
					"productname": "Cosminexus Component Container",
					"cpe": {
						"text": "cpe:/a:hitachi:cosminexus_component_container",
						"version": "2.2"
					}
				},
				{
					"name": "日立",
					"productname": "uCosminexus Application Server",
					"cpe": {
						"text": "cpe:/a:hitachi:ucosminexus_application_server",
						"version": "2.2"
					},
					"versionnumber": [
						"(64)",
						"-R"
					]
				},
				{
					"name": "日立",
					"productname": "uCosminexus Application Server Enterprise",
					"cpe": {
						"text": "cpe:/a:hitachi:ucosminexus_application_server_enterprise",
						"version": "2.2"
					}
				},
				{
					"name": "日立",
					"productname": "uCosminexus Application Server Standard",
					"cpe": {
						"text": "cpe:/a:hitachi:ucosminexus_application_server_standard",
						"version": "2.2"
					},
					"versionnumber": [
						"-R"
					]
				},
				{
					"name": "日立",
					"productname": "uCosminexus Developer",
					"cpe": {
						"text": "cpe:/a:hitachi:ucosminexus_developer",
						"version": "2.2"
					}
				},
				{
					"name": "日立",
					"productname": "uCosminexus Developer Professional",
					"cpe": {
						"text": "cpe:/a:hitachi:ucosminexus_developer_professional",
						"version": "2.2"
					},
					"versionnumber": [
						"for Plug-in"
					]
				},
				{
					"name": "日立",
					"productname": "uCosminexus Developer Standard",
					"cpe": {
						"text": "cpe:/a:hitachi:ucosminexus_developer_standard",
						"version": "2.2"
					}
				},
				{
					"name": "日立",
					"productname": "uCosminexus Service Architect",
					"cpe": {
						"text": "cpe:/a:hitachi:ucosminexus_service_architect",
						"version": "2.2"
					}
				},
				{
					"name": "日立",
					"productname": "uCosminexus Service Platform",
					"cpe": {
						"text": "cpe:/a:hitachi:ucosminexus_service_platform",
						"version": "2.2"
					},
					"versionnumber": [
						"(64)"
					]
				}
			]
		},
		"impact": {
			"impactitem": {
				"description": "想定される影響については、ベンダ情報をご確認ください。"
			}
		},
		"solution": {
			"solutionitem": {
				"description": "ベンダより正式な対策が公開されています。ベンダ情報を参照して適切な対策を実施してください。"
			}
		},
		"related": {
			"relateditem": [
				{
					"type": "vendor",
					"name": "Hitachi Software Vulnerability Information",
					"vulinfoid": "hitachi-sec-2021-113",
					"url": "http://www.hitachi.co.jp/Prod/comp/soft1/global/security/info/vuls/hitachi-sec-2021-113/index.html"
				},
				{
					"type": "vendor",
					"name": "ソフトウェア製品セキュリティ情報",
					"vulinfoid": "hitachi-sec-2021-113",
					"url": "https://www.hitachi.co.jp/Prod/comp/soft1/security/info/vuls/hitachi-sec-2021-113/index.html"
				},
				{
					"type": "cwe",
					"name": "JVNDB",
					"vulinfoid": "CWE-noinfo",
					"url": "https://www.ipa.go.jp/security/vuln/scap/cwe.html",
					"title": "情報不足"
				}
			]
		},
		"history": {
			"historyitem": [
				{
					"historyno": "1",
					"datetime": "2021-04-13T15:21:04+09:00",
					"description": "[2021年04月13日]\\n  掲載"
				}
			]
		},
		"datefirstpublished": "2021-04-13T15:21:04+09:00",
		"datelastupdated": "2021-04-13T15:21:04+09:00",
		"datepublic": "2021-04-13T00:00:00+09:00"
	}
}
