{
	"vulinfoid": "JVNDB-2002-000358",
	"vulinfodata": {
		"title": " tcpdump, libpcap にしかけられたトロイの木馬",
		"vulinfodescription": {
			"overview": "日本時間 2002 年11 月11 日(月) 19時ころから数日間に渡って、 www.tcpdump.org において配布している tcpdump, libpcap のソースパッケージが改ざんされ、トロイの木馬がしかけられていました。また、いくつかのミラーサイトからも同様の状態で配布されていた可能性があります。 なお、www.tcpdump.org において、改ざんされたパッケージの配布が停止されたのは、日本時間 2002 年 11 月14 日(木) 0 時頃です。  改ざんされたソースパッケージから tcpdump, libpcap をコンパイルすると、コンパイル中にプログラムが起動し、ある特定の IP アドレスのポート番号 80/tcp, 1963/tcp に接続します。"
		},
		"affected": {
			"affecteditem": [
				{
					"name": "The Tcpdump Group",
					"productname": "tcpdump",
					"cpe": {
						"text": "cpe:/a:tcpdump:tcpdump",
						"version": "2.2"
					}
				}
			]
		},
		"impact": {
			"impactitem": {
				"description": "遠隔から第三者が tcpdump にしかけられたトロイの木馬にアクセスし、tcpdump をコンパイルしたユーザの権限を取得する可能性があります。"
			}
		},
		"solution": {
			"solutionitem": {}
		},
		"related": {
			"relateditem": [
				{
					"type": "advisory",
					"name": "CERT Advisory",
					"vulinfoid": "IN-2001-06",
					"url": "http://www.cert.org/incident_notes/IN-2001-06.html"
				},
				{
					"type": "advisory",
					"name": "JVN",
					"vulinfoid": "JVNCA-2002-30",
					"url": "http://jvn.jp/cert/JVNCA-2002-30/"
				}
			]
		},
		"history": {
			"historyitem": [
				{
					"historyno": "0",
					"datetime": "2018-02-17T10:37:52+09:00",
					"description": "[2009年04月03日]\\n  掲載"
				}
			]
		},
		"datefirstpublished": "2009-04-03T10:04:10+09:00",
		"datelastupdated": "2009-04-03T10:04:10+09:00",
		"datepublic": "2002-11-18T00:00:00+09:00"
	}
}
