{
  "vulinfoid": "JVNDB-2003-000386",
  "vulinfodata": {
    "title": "GNU Project FTP サーバへの侵害が確認される",
    "vulinfodescription": {
      "overview": "GNU Project が運用している FTP サーバ gnuftp.gnu.org (別名 ftp.gnu.org, alpha.gnu.org ) が何者かにより侵害されたことが確認されました。侵害は 2003 年 3 月頃に発生した可能性が高く、GNU Project では 2003 年 7 月末にその侵害を確認するに至っています。 2003 年 8 月 2 日に侵害された FTP サーバのリプレースを実施、日本時間 2003 年 8 月 14 日時点でファイルのチェックサム検証作業を継続実施中と報告しています。"
    },
    "affected": {
      "affecteditem": [
        {
          "name": "GNU Project",
          "productname": "GNU GCC",
          "cpe": {
            "text": "cpe:/a:gnu:gcc",
            "version": "2.2"
          },
          "versionnumber": [
            "他"
          ]
        }
      ]
    },
    "impact": {
      "impactitem": {
        "description": "gnuftp.gnu.org において配布しているソースパッケージが改ざんされ、バックドア、トロイの木馬などの悪質なコードがしかけられていた可能性があります。また、いくつかのミラーサイトからも同様の状態で配布されていた可能性があります。 "
      }
    },
    "solution": {
      "solutionitem": {}
    },
    "related": {
      "relateditem": [
        {
          "type": "advisory",
          "name": "JVN",
          "vulinfoid": "JVNCA-2003-21",
          "url": "http://jvn.jp/cert/JVNCA-2003-21/"
        }
      ]
    },
    "history": {
      "historyitem": [
        {
          "historyno": "0",
          "datetime": "2018-02-17T10:37:52+09:00",
          "description": "[2009年04月03日]\\n  掲載"
        }
      ]
    },
    "datefirstpublished": "2009-04-03T10:07:35+09:00",
    "datelastupdated": "2009-04-03T10:07:35+09:00",
    "datepublic": "2003-08-14T00:00:00+09:00"
  }
}
